{
  "product": "Rimowa Original Cabin suitcase",
  "slug": "rimowa_original_cabin_suitcase",
  "model_a": "baseline",
  "model_b": "dpo",
  "resolved": {
    "headline": {
      "winner": "baseline",
      "stable": true
    },
    "visual_concept": {
      "winner": "dpo",
      "stable": true
    },
    "strategic_thinking": {
      "winner": "baseline",
      "stable": true
    },
    "brand_alignment": {
      "winner": "TIE",
      "stable": true
    },
    "overall": {
      "winner": "baseline",
      "stable": true
    }
  }
}